luqum/__init__.py
luqum/auto_head_tail.py
luqum/check.py
luqum/deprecated_utils.py
luqum/exceptions.py
luqum/head_tail.py
luqum/naming.py
luqum/parser.py
luqum/parsetab.py
luqum/pretty.py
luqum/tree.py
luqum/utils.py
luqum/visitor.py
luqum/elasticsearch/__init__.py
luqum/elasticsearch/nested.py
luqum/elasticsearch/schema.py
luqum/elasticsearch/tree.py
luqum/elasticsearch/visitor.py
monsterluqum-0.0.3.dist-info/LICENSE
monsterluqum-0.0.3.dist-info/LICENSE.Apache2
monsterluqum-0.0.3.dist-info/LICENSE.LGPLv3
monsterluqum-0.0.3.dist-info/METADATA
monsterluqum-0.0.3.dist-info/WHEEL
monsterluqum-0.0.3.dist-info/top_level.txt
monsterluqum-0.0.3.dist-info/RECORD
