Metadata-Version: 2.1
Name: monsterluqum
Version: 0.0.3
Summary: A Lucene query parser generating ElasticSearch queries and more !
Home-page: https://github.com/kshitij91/luqum
Author: Kshitij
Author-email: kshitij.solr@gmail.com
License: UNKNOWN
Platform: UNKNOWN
Classifier: Development Status :: 4 - Beta
Classifier: License :: OSI Approved :: GNU Lesser General Public License v3 or later (LGPLv3+)
Classifier: License :: OSI Approved :: Apache Software License
Classifier: Intended Audience :: Developers
Classifier: Programming Language :: Python
Classifier: Programming Language :: Python :: 3.6
Classifier: Programming Language :: Python :: 3.7
Classifier: Programming Language :: Python :: 3.8
License-File: LICENSE.Apache2
License-File: LICENSE
License-File: LICENSE.LGPLv3
Requires-Dist: ply (>=3.11)
